llmio/__init__.py
llmio/agent.py
llmio/clients.py
llmio/errors.py
llmio/function_parser.py
llmio/models.py
llmio/py.typed
llmio/types.py
llmio-0.10.4.dist-info/LICENSE
llmio-0.10.4.dist-info/METADATA
llmio-0.10.4.dist-info/WHEEL
llmio-0.10.4.dist-info/RECORD
