Metadata-Version: 2.3
Name: llmio
Version: 0.10.4
Summary: Easily connect large language models into your application
Home-page: https://github.com/badgeir/llmio
License: MIT
Author: Peter Leupi
Requires-Python: >=3.10,<4.0
Classifier: License :: OSI Approved :: MIT License
Classifier: Programming Language :: Python :: 3
Classifier: Programming Language :: Python :: 3.10
Classifier: Programming Language :: Python :: 3.11
Classifier: Programming Language :: Python :: 3.12
Classifier: Programming Language :: Python :: 3.13
Requires-Dist: openai (>=1.41.0)
Requires-Dist: pydantic (>=2.0.0)
Requires-Dist: typing-extensions (>=4.12.2)
Project-URL: Documentation, https://github.com/badgeir/llmio
Project-URL: Repository, https://github.com/badgeir/llmio
